enrichmap/__init__.py
enrichmap/_version.py
enrichmap/plotting/__init__.py
enrichmap/plotting/_cross_moran_scatter.py
enrichmap/plotting/_gene_contributions_heatmap.py
enrichmap/plotting/_gene_contributions_pca.py
enrichmap/plotting/_morans_correlogram.py
enrichmap/plotting/_signature_correlation_heatmap.py
enrichmap/plotting/_spatial_enrichmap.py
enrichmap/plotting/_spatial_metrics.py
enrichmap/plotting/_variogram.py
enrichmap/plotting/_variogram_all.py
enrichmap/tools/__init__.py
enrichmap/tools/_cluster_gene_correlation.py
enrichmap/tools/_compute_f1_scores.py
enrichmap/tools/_compute_spatial_metrics.py
enrichmap/tools/_generate_binary_labels.py
enrichmap/tools/_infer_gene_weights.py
enrichmap/tools/_permutation_test.py
enrichmap/tools/_score.py
enrichmap-0.1.18.dist-info/METADATA
enrichmap-0.1.18.dist-info/WHEEL
enrichmap-0.1.18.dist-info/licenses/LICENSE
enrichmap-0.1.18.dist-info/RECORD
