Metadata-Version: 2.4
Name: enrichmap
Version: 0.1.18
Summary: EnrichMap: Spatially informed enrichment analysis for functional interpretation of spatial transcriptomics
Project-URL: Documentation, https://enrichmap.readthedocs.io/en/stable
Project-URL: Homepage, https://github.com/secrierlab/enrichmap
Project-URL: Issues, https://github.com/secrierlab/EnrichMap/issues
Project-URL: Source, https://github.com/secrierlab/enrichmap
Project-URL: Bluesky, https://bsky.app/profile/cenkcelik.bsky.social
Project-URL: Twitter, https://x.com/_cenk
Author-email: "C. Celik" <cenk.celik@proton.me>
License: GPL-3.0-only
License-File: LICENSE
Classifier: License :: OSI Approved :: GNU General Public License v3 (GPLv3)
Classifier: Operating System :: OS Independent
Classifier: Programming Language :: Python :: 3
Requires-Python: >=3.10
Requires-Dist: adjusttext
Requires-Dist: numpy
Requires-Dist: pygam
Requires-Dist: scanpy
Requires-Dist: scikit-gstat
Requires-Dist: scikit-learn
Requires-Dist: scipy
Requires-Dist: splot
Requires-Dist: statannotations
